cpas_toolbox/__init__.py
cpas_toolbox/camera_utils.py
cpas_toolbox/cpas_method.py
cpas_toolbox/evaluate.py
cpas_toolbox/metrics.py
cpas_toolbox/pointset_utils.py
cpas_toolbox/quaternion_utils.py
cpas_toolbox/utils.py
cpas_toolbox/config/all_baselines.yaml
cpas_toolbox/config/asmnet.yaml
cpas_toolbox/config/cass.yaml
cpas_toolbox/config/crnet.yaml
cpas_toolbox/config/dpdn.yaml
cpas_toolbox/config/icaps.yaml
cpas_toolbox/config/nocs.yaml
cpas_toolbox/config/rbppose.yaml
cpas_toolbox/config/real275.yaml
cpas_toolbox/config/real275_camera.json
cpas_toolbox/config/real275_renderoptions.json
cpas_toolbox/config/redwood75.yaml
cpas_toolbox/config/sdfest.yaml
cpas_toolbox/config/sgpa.yaml
cpas_toolbox/config/spd.yaml
cpas_toolbox/cpas_methods/__init__.py
cpas_toolbox/cpas_methods/asmnet.py
cpas_toolbox/cpas_methods/cass.py
cpas_toolbox/cpas_methods/crnet.py
cpas_toolbox/cpas_methods/dpdn.py
cpas_toolbox/cpas_methods/icaps.py
cpas_toolbox/cpas_methods/rbppose.py
cpas_toolbox/cpas_methods/sdfest.py
cpas_toolbox/cpas_methods/sgpa.py
cpas_toolbox/cpas_methods/spd.py
cpas_toolbox/cpas_methods/_asmnet/__init__.py
cpas_toolbox/cpas_methods/_asmnet/common3Dfunc.py
cpas_toolbox/cpas_methods/_asmnet/cr6d_utils.py
cpas_toolbox/cpas_methods/_asmnet/ASM_Net/__init__.py
cpas_toolbox/cpas_methods/_asmnet/ASM_Net/pointnet.py
cpas_toolbox/cpas_methods/_asmnet/asm_pcd/__init__.py
cpas_toolbox/cpas_methods/_asmnet/asm_pcd/asm.py
cpas_toolbox/cpas_methods/_cass/__init__.py
cpas_toolbox/cpas_methods/_cass/cass/__init__.py
cpas_toolbox/cpas_methods/_cass/cass/extractors.py
cpas_toolbox/cpas_methods/_cass/cass/foldingnet.py
cpas_toolbox/cpas_methods/_cass/cass/models.py
cpas_toolbox/cpas_methods/_cass/cass/network.py
cpas_toolbox/cpas_methods/_cass/cass/pointnet.py
cpas_toolbox/cpas_methods/_cass/cass/pspnet.py
cpas_toolbox/cpas_methods/_cass/cass/transformations.py
cpas_toolbox/cpas_methods/_cass/cass/utils.py
cpas_toolbox/cpas_methods/_cass/datasets/__init__.py
cpas_toolbox-1.0.0.dist-info/LICENSE
cpas_toolbox-1.0.0.dist-info/METADATA
cpas_toolbox-1.0.0.dist-info/WHEEL
cpas_toolbox-1.0.0.dist-info/top_level.txt
cpas_toolbox-1.0.0.dist-info/RECORD
