Metadata-Version: 2.1
Name: cpas-toolbox
Version: 1.0.0
Summary: Toolbox to evaluate categorical pose and shape estimation
Home-page: https://github.com/roym899/pose_and_shape_evaluation
Author: Leonard Bruns
Author-email: roym899@gmail.com
Classifier: Programming Language :: Python :: 3
Classifier: License :: OSI Approved :: MIT License
Classifier: Operating System :: OS Independent
Classifier: Development Status :: 4 - Beta
Classifier: Intended Audience :: Science/Research
Requires-Python: >=3.7
License-File: LICENSE
Requires-Dist: easydict
Requires-Dist: filterpy
Requires-Dist: gdown
Requires-Dist: matplotlib (<3.6)
Requires-Dist: ninja
Requires-Dist: numba
Requires-Dist: numpy
Requires-Dist: open3d
Requires-Dist: opencv-python-headless
Requires-Dist: Pillow
Requires-Dist: plyfile
Requires-Dist: requests
Requires-Dist: scipy
Requires-Dist: scikit-image
Requires-Dist: sdfest
Requires-Dist: tikzplotlib
Requires-Dist: tqdm
Requires-Dist: torch
Requires-Dist: torchvision
Requires-Dist: transforms3d
Requires-Dist: trimesh
Requires-Dist: yoco
